.gitignore
README.md
pyproject.toml
setup.py
uv.lock
.github/workflows/python.yml
.github/workflows/test-build-deploy.yml
scripts/dev-checks.sh
src/monitor/__init__.py
src/monitor/app.py
src/scripts/__init__.py
src/scripts/copy_arctic_data.py
src/tradingo/__init__.py
src/tradingo/_backtest.c
src/tradingo/_backtest.pyx
src/tradingo/api.py
src/tradingo/backtest.py
src/tradingo/cli.py
src/tradingo/config.py
src/tradingo/dag.py
src/tradingo/engine.py
src/tradingo/plotting.py
src/tradingo/portfolio.py
src/tradingo/settings.py
src/tradingo/symbols.py
src/tradingo/utils.py
src/tradingo.egg-info/PKG-INFO
src/tradingo.egg-info/SOURCES.txt
src/tradingo.egg-info/dependency_links.txt
src/tradingo.egg-info/entry_points.txt
src/tradingo.egg-info/requires.txt
src/tradingo.egg-info/top_level.txt
src/tradingo/backfill/__init__.py
src/tradingo/backfill/dukascopy.py
src/tradingo/backfill/forexsb.py
src/tradingo/sampling/__init__.py
src/tradingo/sampling/ig.py
src/tradingo/sampling/instruments.py
src/tradingo/sampling/yf.py
src/tradingo/templates/__init__.py
src/tradingo/templates/downstream_tasks.yaml
src/tradingo/templates/portfolio_construction.yaml
src/tradingo/templates/instruments/forexsb.yaml
src/tradingo/templates/instruments/ig-trading.yaml
src/tradingo/templates/instruments/yfinance.yaml
test/__init__.py
test/tradingo/__init__.py
test/tradingo/conftest.py
test/tradingo/test_api.py
test/tradingo/test_backtest.py
test/tradingo/test_config.py
test/tradingo/test_dag.py
test/tradingo/test_env_provider.py
test/tradingo/test_sampling.py
test/tradingo/utils.py