Metadata-Version: 2.4
Name: tradingo
Version: 0.1.1
Summary: Instrument price store
Author-email: Rory McStay <rory@rorymcstay.com>
Classifier: Programming Language :: Python :: 3
Requires-Python: >=3.11
Requires-Dist: numpy
Requires-Dist: numba
Requires-Dist: pandas
Requires-Dist: pandera
Requires-Dist: arcticdb
Requires-Dist: PyYAML
Requires-Dist: yfinance
Requires-Dist: lxml
Requires-Dist: pandas_market_calendars
Requires-Dist: trading_ig
Requires-Dist: riskfolio-lib
Requires-Dist: tenacity
Requires-Dist: lightgbm>=4.6.0
Requires-Dist: pycountry
Requires-Dist: ipython>=9.1.0
Requires-Dist: tabula>=1.0.5
Requires-Dist: tabula-py>=2.10.0
